odoo/addons/sale_global_discount/README.rst
odoo/addons/sale_global_discount/__init__.py
odoo/addons/sale_global_discount/__manifest__.py
odoo/addons/sale_global_discount/i18n/es.po
odoo/addons/sale_global_discount/i18n/sale_global_discount.pot
odoo/addons/sale_global_discount/models/__init__.py
odoo/addons/sale_global_discount/models/sale_order.py
odoo/addons/sale_global_discount/readme/CONFIGURE.rst
odoo/addons/sale_global_discount/readme/CONTRIBUTORS.rst
odoo/addons/sale_global_discount/readme/DESCRIPTION.rst
odoo/addons/sale_global_discount/readme/ROADMAP.rst
odoo/addons/sale_global_discount/readme/USAGE.rst
odoo/addons/sale_global_discount/static/description/icon.png
odoo/addons/sale_global_discount/static/description/icon.svg
odoo/addons/sale_global_discount/static/description/index.html
odoo/addons/sale_global_discount/tests/__init__.py
odoo/addons/sale_global_discount/tests/test_sale_global_discount.py
odoo/addons/sale_global_discount/views/report_sale_order.xml
odoo/addons/sale_global_discount/views/sale_order_views.xml
odoo11_addon_sale_global_discount-11.0.1.0.3.dist-info/METADATA
odoo11_addon_sale_global_discount-11.0.1.0.3.dist-info/WHEEL
odoo11_addon_sale_global_discount-11.0.1.0.3.dist-info/top_level.txt
odoo11_addon_sale_global_discount-11.0.1.0.3.dist-info/RECORD
